fiddle/__init__.py
fiddle/building.py
fiddle/config.py
fiddle/config_test.py
fiddle/daglish.py
fiddle/daglish_test.py
fiddle/graphviz.py
fiddle/history.py
fiddle/history_test.py
fiddle/materialize.py
fiddle/materialize_test.py
fiddle/module_reflection.py
fiddle/module_reflection_test.py
fiddle/module_reflection_test_module.py
fiddle/printing.py
fiddle/printing_test.py
fiddle/tag_type.py
fiddle/tagging.py
fiddle/tagging_test.py
fiddle/tagging_test_module.py
fiddle/_src/__init__.py
fiddle/_src/field_metadata.py
fiddle/_src/mutate_buildable.py
fiddle/_src/mutate_buildable_test.py
fiddle/absl_flags/__init__.py
fiddle/absl_flags/flags.py
fiddle/absl_flags/sample_module_for_flags_test.py
fiddle/absl_flags/example/__init__.py
fiddle/absl_flags/example/business_logic.py
fiddle/absl_flags/example/configs.py
fiddle/absl_flags/example/example.py
fiddle/absl_flags/example/tags.py
fiddle/codegen/__init__.py
fiddle/codegen/codegen.py
fiddle/codegen/codegen_diff.py
fiddle/codegen/codegen_test.py
fiddle/codegen/formatting_utilities.py
fiddle/codegen/import_manager.py
fiddle/codegen/import_manager_test.py
fiddle/codegen/mini_ast.py
fiddle/codegen/namespace.py
fiddle/codegen/namespace_test.py
fiddle/codegen/py_val_to_cst_converter.py
fiddle/codegen/py_val_to_cst_converter_test.py
fiddle/codegen/special_value_codegen.py
fiddle/codegen/test_util.py
fiddle/codegen/test_submodule/__init__.py
fiddle/codegen/test_submodule/test_util.py
fiddle/examples/__init__.py
fiddle/examples/colabs/__init__.py
fiddle/experimental/__init__.py
fiddle/experimental/arg_factory.py
fiddle/experimental/arg_factory_test.py
fiddle/experimental/auto_config.py
fiddle/experimental/auto_config_policy.py
fiddle/experimental/auto_config_test.py
fiddle/experimental/autofill.py
fiddle/experimental/autofill_test.py
fiddle/experimental/daglish_legacy.py
fiddle/experimental/daglish_legacy_test.py
fiddle/experimental/dataclasses.py
fiddle/experimental/dataclasses_test.py
fiddle/experimental/dict_config.py
fiddle_config-0.2.2.dist-info/LICENSE
fiddle_config-0.2.2.dist-info/METADATA
fiddle_config-0.2.2.dist-info/WHEEL
fiddle_config-0.2.2.dist-info/top_level.txt
fiddle_config-0.2.2.dist-info/RECORD
